nodify_plugin/__init__.py
nodify_plugin/plugin.py
nodify_plugin/static/index.html
nodify_plugin/static/index.js
nodify_plugin/utils/__init__.py
nodify_plugin/utils/dataframe.py
nodify_plugin/utils/plot.py
nodify_plugin/utils/range.py
nodify_plugin-0.1.6.dist-info/LICENSE.md
nodify_plugin-0.1.6.dist-info/METADATA
nodify_plugin-0.1.6.dist-info/WHEEL
nodify_plugin-0.1.6.dist-info/entry_points.txt
nodify_plugin-0.1.6.dist-info/top_level.txt
nodify_plugin-0.1.6.dist-info/RECORD
