Metadata-Version: 2.1
Name: nodify-plugin
Version: 0.1.6
Summary: Nodify Tensorboard Plugin.
Author: Trainy Team
Author-email: founders@trainy.ai
License: BSD-3
Keywords: pytorch tensorboard profile plugin
License-File: LICENSE.md
Requires-Dist: HolisticTraceAnalysis
Requires-Dist: posthog
Requires-Dist: tensorboard
